bloow/__init__.py
bloow/version.py
bloow-0.0.0.dist-info/AUTHORS
bloow-0.0.0.dist-info/LICENSE
bloow-0.0.0.dist-info/METADATA
bloow-0.0.0.dist-info/NOTICE
bloow-0.0.0.dist-info/WHEEL
bloow-0.0.0.dist-info/top_level.txt
bloow-0.0.0.dist-info/zip-safe
bloow-0.0.0.dist-info/RECORD
